siren/__init__.py
siren/init.py
siren/siren.py
siren_torch-1.1.dist-info/LICENSE
siren_torch-1.1.dist-info/METADATA
siren_torch-1.1.dist-info/WHEEL
siren_torch-1.1.dist-info/top_level.txt
siren_torch-1.1.dist-info/RECORD
