Metadata-Version: 2.1
Name: siren-torch
Version: 1.1
Summary: PyTorch implementation of Sinusodial Representation networks (SIREN)
Home-page: https://github.com/dalmia/siren
Author: Aman Dalmia
Author-email: amandalmia18@gmail.com
License: UNKNOWN
Platform: UNKNOWN
Classifier: Programming Language :: Python :: 3
Classifier: License :: OSI Approved :: MIT License
Classifier: Operating System :: OS Independent
Requires-Python: >=3.5.2
